motiondetector/__init__.py
motiondetector/__main__.py
motiondetector/utils/Class.py
motiondetector/utils/__init__.py
motiondetector/utils/functions.py
motion_detector-1.0.4.dist-info/LICENSE
motion_detector-1.0.4.dist-info/METADATA
motion_detector-1.0.4.dist-info/WHEEL
motion_detector-1.0.4.dist-info/top_level.txt
motion_detector-1.0.4.dist-info/RECORD
