Metadata-Version: 2.1
Name: motion-detector
Version: 1.0.4
Home-page: https://github.com/Ridoineel/motion_detector/log-module
Author: RidoineEl
Author-email: ridoineelofficiel@gmail.com
Project-URL: Bug Tracker, https://github.com/Ridoineel/motion_detector/log-module/issues
Classifier: Programming Language :: Python :: 3
Classifier: License :: OSI Approved :: MIT License
Classifier: Operating System :: OS Independent
Requires-Python: >=3.6
License-File: LICENSE
Requires-Dist: opencv-python
Requires-Dist: numpy
Requires-Dist: scipy
Requires-Dist: matplotlib
Requires-Dist: pillow
